SKOpts.py
Tune_Bagging.py
Tune_BernoulliNB.py
Tune_CatBoost.py
Tune_DecisionTree.py
Tune_Extratrees.py
Tune_GaussianNB.py
Tune_HistGradientBoost.py
Tune_KNeighbors.py
Tune_Lgbm.py
Tune_LogisticRegression.py
Tune_MLP.py
Tune_RandomForest.py
Tune_Ridge.py
Tune_RidgeCVs.py
Tune_Xgboost.py
Voting_Ensemble_weights.py
__init__.py
SkOpts-0.0.1.dist-info/License.txt
SkOpts-0.0.1.dist-info/METADATA
SkOpts-0.0.1.dist-info/WHEEL
SkOpts-0.0.1.dist-info/top_level.txt
SkOpts-0.0.1.dist-info/RECORD
