Metadata-Version: 2.1
Name: SkOpts
Version: 0.0.1
Summary: Hyperparameters tuning of machine learning models provided by sklearn library using optuna
Author-email: Sunny Dial <dialsunny91@gmail.com>
Project-URL: Homepage, https://github.com/DSun91/SKOpts
Project-URL: Bug Tracker, https://github.com/DSun91/SKOpts/issues
Classifier: Programming Language :: Python :: 3
Classifier: License :: OSI Approved :: MIT License
Classifier: Operating System :: OS Independent
Requires-Python: >=3.8
License-File: License.txt
